Metadata-Version: 2.1
Name: jija-sqlalchemy
Version: 0.1
Summary: SQLAlchemy driver for Jija framework
Home-page: https://gitlab.com/by_dezz/jija-sqlalchemy
Author: Kain
Author-email: kainedezz.2000@gmail.com
License: UNKNOWN
Platform: UNKNOWN
